LICENSE
MANIFEST.in
README.md
setup.cfg
setup.py
./topn/topn.pyx
./topn/topn_parallel.cpp
./topn/topn_source.cpp
./topn/topn_threaded.pyx
topn/__init__.py
topn/awesome_topn.py
topn/topn.pyx
topn/topn_parallel.cpp
topn/topn_parallel.h
topn/topn_source.cpp
topn/topn_source.h
topn/topn_threaded.pyx
topn.egg-info/.gitignore
topn.egg-info/PKG-INFO
topn.egg-info/SOURCES.txt
topn.egg-info/dependency_links.txt
topn.egg-info/not-zip-safe
topn.egg-info/requires.txt
topn.egg-info/top_level.txt
topn/test/__init__.py
topn/test/test_topn.py