Metadata-Version: 2.1
Name: topn
Version: 0.0.5
Summary: This package boosts a group-wise nlargest sort
Home-page: https://github.com/ParticularMiner/topn
Author: Particular Miner
Author-email: particularminer@fake.com
License: MIT
Download-URL: https://github.com/ParticularMiner/topn/archive/refs/tags/v0.0.5.tar.gz
Keywords: nlargest hstack csr csc scipy cython
Platform: UNKNOWN
